fiftyone/__init__.py
fiftyone/__public__.py
fiftyone/constants.py
fiftyone/core/__init__.py
fiftyone/core/aggregations.py
fiftyone/core/annotation.py
fiftyone/core/brain.py
fiftyone/core/cli.py
fiftyone/core/client.py
fiftyone/core/clips.py
fiftyone/core/collections.py
fiftyone/core/config.py
fiftyone/core/context.py
fiftyone/core/dataset.py
fiftyone/core/document.py
fiftyone/core/evaluation.py
fiftyone/core/expressions.py
fiftyone/core/fields.py
fiftyone/core/frame.py
fiftyone/core/frame_utils.py
fiftyone/core/labels.py
fiftyone/core/media.py
fiftyone/core/metadata.py
fiftyone/core/models.py
fiftyone/core/patches.py
fiftyone/core/runs.py
fiftyone/core/sample.py
fiftyone/core/service.py
fiftyone/core/session.py
fiftyone/core/singletons.py
fiftyone/core/stages.py
fiftyone/core/state.py
fiftyone/core/uid.py
fiftyone/core/utils.py
fiftyone/core/validation.py
fiftyone/core/video.py
fiftyone/core/view.py
fiftyone/core/odm/__init__.py
fiftyone/core/odm/database.py
fiftyone/core/odm/dataset.py
fiftyone/core/odm/document.py
fiftyone/core/odm/frame.py
fiftyone/core/odm/mixins.py
fiftyone/core/odm/runs.py
fiftyone/core/odm/sample.py
fiftyone/core/plots/__init__.py
fiftyone/core/plots/base.py
fiftyone/core/plots/manager.py
fiftyone/core/plots/matplotlib.py
fiftyone/core/plots/plotly.py
fiftyone/core/plots/utils.py
fiftyone/core/plots/views.py
fiftyone/migrations/__init__.py
fiftyone/migrations/runner.py
fiftyone/migrations/revisions/v0_11_2.py
fiftyone/migrations/revisions/v0_13_0.py
fiftyone/migrations/revisions/v0_14_0.py
fiftyone/migrations/revisions/v0_6_2.py
fiftyone/migrations/revisions/v0_6_5.py
fiftyone/migrations/revisions/v0_7_2.py
fiftyone/migrations/revisions/v0_7_3.py
fiftyone/migrations/revisions/v0_7_4.py
fiftyone/migrations/revisions/v0_8_0.py
fiftyone/migrations/revisions/v0_9_4.py
fiftyone/migrations/revisions/admin/v0_7_1.py
fiftyone/recipes/image_deduplication_helpers.py
fiftyone/resources/cvat_image_annotation_template.xml
fiftyone_eval_only-0.14.3.dist-info/LICENSE
fiftyone_eval_only-0.14.3.dist-info/METADATA
fiftyone_eval_only-0.14.3.dist-info/WHEEL
fiftyone_eval_only-0.14.3.dist-info/entry_points.txt
fiftyone_eval_only-0.14.3.dist-info/top_level.txt
fiftyone_eval_only-0.14.3.dist-info/RECORD
