Metadata-Version: 2.1
Name: fiftyone-eval-only
Version: 0.14.3
Summary: FiftyOne, for evaluation only.
Home-page: UNKNOWN
Author: Voxel51, Inc.
Author-email: 
License: Apache
Platform: UNKNOWN
Classifier: Development Status :: 4 - Beta
Classifier: Intended Audience :: Developers
Classifier: Intended Audience :: Science/Research
Classifier: License :: OSI Approved :: Apache Software License
Classifier: Topic :: Scientific/Engineering :: Artificial Intelligence
Classifier: Topic :: Scientific/Engineering :: Image Processing
Classifier: Topic :: Scientific/Engineering :: Image Recognition
Classifier: Topic :: Scientific/Engineering :: Information Analysis
Classifier: Topic :: Scientific/Engineering :: Visualization
Classifier: Operating System :: MacOS :: MacOS X
Classifier: Operating System :: POSIX :: Linux
Classifier: Operating System :: Microsoft :: Windows
Classifier: Programming Language :: Python :: 3
Classifier: Programming Language :: Python :: 3.6
Classifier: Programming Language :: Python :: 3.7
Classifier: Programming Language :: Python :: 3.8
Classifier: Programming Language :: Python :: 3.9
Requires-Python: >=3.6
License-File: LICENSE
Requires-Dist: aiofiles
Requires-Dist: argcomplete
Requires-Dist: boto3
Requires-Dist: Deprecated
Requires-Dist: eventlet
Requires-Dist: future
Requires-Dist: ipywidgets (>=7.0.0)
Requires-Dist: Jinja2
Requires-Dist: kaleido
Requires-Dist: matplotlib
Requires-Dist: mongoengine (==0.20.0)
Requires-Dist: motor (<3,>=2.3)
Requires-Dist: numpy
Requires-Dist: opencv-python-headless
Requires-Dist: packaging
Requires-Dist: pandas
Requires-Dist: Pillow (>=6.2)
Requires-Dist: plotly (<5,>=4.14)
Requires-Dist: pprintpp
Requires-Dist: psutil
Requires-Dist: pymongo (<4,>=3.11)
Requires-Dist: pytz
Requires-Dist: PyYAML
Requires-Dist: retrying
Requires-Dist: scikit-learn
Requires-Dist: scikit-image
Requires-Dist: setuptools
Requires-Dist: tabulate
Requires-Dist: tornado (<7,>=5.1.1)
Requires-Dist: xmltodict
Requires-Dist: universal-analytics-python3 (<2,>=1.0.1)
Requires-Dist: voxel51-eta (<0.7,>=0.6.1)
Requires-Dist: fiftyone-brain (<0.8,>=0.7.2)
Requires-Dist: fiftyone-db (<0.4,>=0.3)
Provides-Extra: desktop
Requires-Dist: fiftyone-desktop (<0.20,>=0.19.1) ; extra == 'desktop'
